antares/__init__.py
antares/cli.py
antares/config.py
antares/config_loader.py
antares/errors.py
antares/logger.py
antares/client/__init__.py
antares/client/rest.py
antares/client/tcp.py
antares/models/ship.py
antares/models/track.py
antares_python-1.0.0.dist-info/licenses/LICENSE
antares_python-1.0.0.dist-info/METADATA
antares_python-1.0.0.dist-info/WHEEL
antares_python-1.0.0.dist-info/entry_points.txt
antares_python-1.0.0.dist-info/top_level.txt
antares_python-1.0.0.dist-info/RECORD
