Metadata-Version: 2.4
Name: antares-python
Version: 1.0.0
Summary: Python interface for the Antares simulation software
Author-email: Juan Sebastian Urrea-Lopez <js.urrea@uniandes.edu.co>, Camilo Barreto-Reyes <c.barretor@uniandes.edu.co>, Mario Linares-Vásquez <m.linaresv@uniandes.edu.co>
Requires-Python: >=3.13
License-File: LICENSE
Requires-Dist: pydantic>=2.11.3
Requires-Dist: pydantic-settings>=2.8.1
Requires-Dist: httpx>=0.28.1
Requires-Dist: typer>=0.15.2
Requires-Dist: rich>=13.0
Requires-Dist: tomli>=2.2.1
Provides-Extra: dev
Requires-Dist: taskipy==1.14.1; extra == "dev"
Requires-Dist: build==1.2.2.post1; extra == "dev"
Requires-Dist: mypy==1.15.0; extra == "dev"
Requires-Dist: pytest==8.3.5; extra == "dev"
Requires-Dist: pytest-cov==6.1.1; extra == "dev"
Requires-Dist: pytest-mock==3.14.0; extra == "dev"
Requires-Dist: pytest-asyncio>=0.26.0; extra == "dev"
Requires-Dist: ruff==0.11.8; extra == "dev"
Dynamic: license-file
